Metadata-Version: 2.1
Name: appear
Version: 1.2.3
Summary: Make program internals appear in the browser
Home-page: https://github.com/andrew-houghton/appear
Author: Andrew Houghton
Author-email: houghtonandrew0@gmail.com
License: UNKNOWN
Platform: UNKNOWN
